homematic/__init__.py
homematic/__version__.py
homematic/hmrpc.py
homematic/jsonrpc.py
homematic/list_devices.py
PJHomematic-0.1.dist-info/LICENSE
PJHomematic-0.1.dist-info/METADATA
PJHomematic-0.1.dist-info/WHEEL
PJHomematic-0.1.dist-info/top_level.txt
PJHomematic-0.1.dist-info/RECORD
