Metadata-Version: 2.1
Name: PJHomematic
Version: 0.1
Summary: An interface to the Homematic JSON-API
Author-email: Andreas Schawo <andreas@schawo.de>
Project-URL: Homepage, https://github.com/gitandy/PJHomematic
Project-URL: Bug Tracker, https://github.com/gitandy/PJHomematic/issues
Classifier: Development Status :: 4 - Beta
Classifier: Intended Audience :: Developers
Classifier: Intended Audience :: Other Audience
Classifier: Operating System :: OS Independent
Classifier: Programming Language :: Python :: 3 :: Only
Classifier: Programming Language :: Python :: 3.9
Classifier: Programming Language :: Python :: 3.10
Classifier: Programming Language :: Python :: 3.11
Classifier: Programming Language :: Python :: 3.12
Classifier: Topic :: Home Automation
Requires-Python: >=3.9
License-File: LICENSE
Requires-Dist: json5
Requires-Dist: requests
Requires-Dist: lxml
Provides-Extra: extra
Requires-Dist: openpyxl ; extra == 'extra'
